COPYING.txt
MANIFEST.in
README.md
requirements.txt
setup.py
app_report/__init__.py
app_report/client.py
app_report/configuration.py
app_report/decoder.py
app_report/errors.py
app_report/signer.py
app_report.egg-info/PKG-INFO
app_report.egg-info/SOURCES.txt
app_report.egg-info/dependency_links.txt
app_report.egg-info/requires.txt
app_report.egg-info/top_level.txt
app_report/api/__init__.py
app_report/api/base.py
app_report/api/jasper.py
app_report/helpers/__init__.py
app_report/helpers/reports/__init__.py
app_report/helpers/reports/jasper_base.py
app_report/helpers/reports/jasper_web2py.py
app_report/helpers/serializers/__init__.py
app_report/helpers/serializers/xml_base.py
app_report/helpers/serializers/xml_web2py.py
app_report/report/__init__.py
app_report/report/jasper.py
test/__init__.py
test/app_report/__init__.py
test/app_report/api/__init__.py
test/app_report/api/fake_api.py
test/app_report/helpers/__init__.py
test/app_report/helpers/fake_web2py_response.py