Metadata-Version: 1.1
Name: app-report
Version: 0.0.3
Summary: Python client to AppReport API
Home-page: https://github.com/simple_services/app_report-python
Author: Lucas D'Avila
Author-email: lucas@lucasdavi.la
License: UNKNOWN
Keywords: pdf,report,jasper,api
Platform: UNKNOWN
Classifier: Programming Language :: Python
Classifier: Programming Language :: Python :: 3
Classifier: License :: OSI Approved :: GNU Lesser General Public License v3 or later (LGPLv3+)
Classifier: Operating System :: OS Independent
Classifier: Intended Audience :: Developers
Classifier: Topic :: Software Development :: Libraries :: Python Modules
Classifier: Environment :: Web Environment
Classifier: Development Status :: 3 - Alpha
